complex_multiply/__init__.py
complex_multiply/multiplication.py
complex_multiply-0.1.0.dist-info/METADATA
complex_multiply-0.1.0.dist-info/WHEEL
complex_multiply-0.1.0.dist-info/top_level.txt
complex_multiply-0.1.0.dist-info/RECORD
