Metadata-Version: 2.1
Name: complex-multiply
Version: 0.1.0
Summary: Demo library
Home-page: https://complex-multiply.readthedocs.io/
Author: Sami Ansari
Author-email: samii.ansari@hotmail.com
License: MIT
Platform: UNKNOWN
Classifier: Intended Audience :: Developers
Classifier: License :: OSI Approved :: MIT License
Classifier: Programming Language :: Python
Classifier: Programming Language :: Python :: 3
Classifier: Programming Language :: Python :: 3.6
Classifier: Programming Language :: Python :: 3.7
Classifier: Programming Language :: Python :: 3.8
Classifier: Programming Language :: Python :: 3.9
Classifier: Operating System :: OS Independent
Requires-Dist: numpy
